mutspec_utils/__init__.py
mutspec_utils/annotation/__init__.py
mutspec_utils/annotation/auxiliary.py
mutspec_utils/annotation/binom_test.py
mutspec_utils/annotation/mut.py
mutspec_utils/annotation/spectra.py
mutspec_utils/annotation/tree.py
mutspec_utils/constants/__init__.py
mutspec_utils/constants/sbs.py
mutspec_utils/draw/__init__.py
mutspec_utils/draw/sbs_orders.py
mutspec_utils/draw/spectra.py
mutspec_utils/io/__init__.py
mutspec_utils/io/auxiliary.py
mutspec_utils/io/states.py
mutspec_utils/utils/__init__.py
mutspec_utils/utils/custom_profile.py
mutspec_utils/utils/logging.py
mutspec_utils/utils/configs/log_settings.yaml
pymutspec/__init__.py
pymutspec/annotation/__init__.py
pymutspec/annotation/auxiliary.py
pymutspec/annotation/binom_test.py
pymutspec/annotation/mut.py
pymutspec/annotation/spectra.py
pymutspec/annotation/tree.py
pymutspec/constants/__init__.py
pymutspec/constants/sbs.py
pymutspec/draw/__init__.py
pymutspec/draw/sbs_orders.py
pymutspec/draw/spectra.py
pymutspec/io/__init__.py
pymutspec/io/auxiliary.py
pymutspec/io/gb.py
pymutspec/io/states.py
pymutspec/utils/__init__.py
pymutspec/utils/custom_profile.py
pymutspec/utils/logging.py
pymutspec/utils/configs/log_settings.yaml
pymutspec-0.0.14.data/scripts/1.terminal_genomes2iqtree_format.py
pymutspec-0.0.14.data/scripts/2.iqtree_states2custom_format.py
pymutspec-0.0.14.data/scripts/2.iqtree_states_parted2custom_format.py
pymutspec-0.0.14.data/scripts/3.collect_mutations.py
pymutspec-0.0.14.data/scripts/alignment2iqtree_states.py
pymutspec-0.0.14.data/scripts/aln2pastml.py
pymutspec-0.0.14.data/scripts/calculate_mutspec.py
pymutspec-0.0.14.data/scripts/calculate_mutspec_pyvolve.py
pymutspec-0.0.14.data/scripts/collect_mutations.py
pymutspec-0.0.14.data/scripts/collect_mutations_parallel.py
pymutspec-0.0.14.data/scripts/concat_mutations.py
pymutspec-0.0.14.data/scripts/filter_aln.py
pymutspec-0.0.14.data/scripts/iqtree_states_add_part.py
pymutspec-0.0.14.data/scripts/multifasta_coding.py
pymutspec-0.0.14.dist-info/licenses/LICENSE
pymutspec-0.0.14.dist-info/METADATA
pymutspec-0.0.14.dist-info/WHEEL
pymutspec-0.0.14.dist-info/top_level.txt
pymutspec-0.0.14.dist-info/RECORD
