Metadata-Version: 2.4
Name: PyMutSpec
Version: 0.0.14
Summary: Mutational spectra analysis package
Author-email: kpotoh <axepon@mail.ru>
License: Copyright (c) 2025 kpotoh
Project-URL: Homepage, https://github.com/mitoclub/PyMutSpec
Project-URL: Changelog, https://github.com/mitoclub/PyMutSpec/blob/master/CHANGELOG.md
Project-URL: Bug Tracker, https://github.com/mitoclub/PyMutSpec/issues
Keywords: Bioinformatics,Genetics,Mutational spectra
Classifier: Operating System :: OS Independent
Classifier: Development Status :: 3 - Alpha
Classifier: Programming Language :: Python :: 3
Classifier: Programming Language :: Python :: 3.8
Classifier: Programming Language :: Python :: 3.9
Classifier: Programming Language :: Python :: 3.10
Classifier: Topic :: Scientific/Engineering
Classifier: Topic :: Scientific/Engineering :: Bio-Informatics
Classifier: Topic :: Software Development :: Libraries :: Python Modules
Classifier: License :: OSI Approved :: MIT License
Requires-Python: >=3.8
License-File: LICENSE
Requires-Dist: numpy<2.0
Requires-Dist: pandas<2.0
Requires-Dist: seaborn==0.12.2
Requires-Dist: biopython>=1.75
Requires-Dist: ete3>=3
Requires-Dist: tqdm
Requires-Dist: PyYAML
Requires-Dist: pytest
Requires-Dist: click
Provides-Extra: dev
Requires-Dist: pytest; extra == "dev"
Requires-Dist: pytest-cov; extra == "dev"
Requires-Dist: flake8; extra == "dev"
Dynamic: license-file
